open_meteo_solar_forecast/__init__.py
open_meteo_solar_forecast/constants.py
open_meteo_solar_forecast/exceptions.py
open_meteo_solar_forecast/models.py
open_meteo_solar_forecast/open_meteo_solar_forecast.py
open_meteo_solar_forecast/py.typed
open_meteo_solar_forecast-0.1.22.dist-info/LICENSE
open_meteo_solar_forecast-0.1.22.dist-info/METADATA
open_meteo_solar_forecast-0.1.22.dist-info/WHEEL
open_meteo_solar_forecast-0.1.22.dist-info/RECORD
