Metadata-Version: 2.3
Name: open-meteo-solar-forecast
Version: 0.1.22
Summary: Asynchronous Python client for getting forecast solar information
License: MIT
Keywords: forecast,solar,power,energy,api,async,client
Author: Rany
Author-email: rany@riseup.net
Maintainer: Rany
Maintainer-email: rany@riseup.net
Requires-Python: >=3.11,<4.0
Classifier: Framework :: AsyncIO
Classifier: Intended Audience :: Developers
Classifier: License :: OSI Approved :: MIT License
Classifier: Natural Language :: English
Classifier: Programming Language :: Python :: 3
Classifier: Programming Language :: Python :: 3.11
Classifier: Programming Language :: Python :: 3.12
Classifier: Programming Language :: Python :: 3.13
Classifier: Topic :: Software Development :: Libraries :: Python Modules
Requires-Dist: aiohttp (>=3.0.0)
Project-URL: Bug Tracker, https://github.com/rany2/open-meteo-solar-forecast/issues
Project-URL: Changelog, https://github.com/rany2/open-meteo-solar-forecast/releases
Project-URL: Documentation, https://github.com/rany2/open-meteo-solar-forecast
Project-URL: Homepage, https://github.com/rany2/open-meteo-solar-forecast
Project-URL: Repository, https://github.com/rany2/open-meteo-solar-forecast
